{
  "qkname": "微笑的约定",
  "data": [
    {
      "npc": "高级魔法师斯泰拉",
      "question": "……看你的脸色不大好啊。<br>发生什么事情了，不妨慢慢说来。",
      "answer": ""
    },
    {
      "npc": "{user_nick}",
      "question": "<FONT color=#662500>（述说在阿勒努特峡谷发生的事情）</FONT>",
      "answer": ""
    },
    {
      "npc": "高级魔法师斯泰拉",
      "question": "黛西就是克隆体的原型？<br>而且还是宝玉……宝玉的碎片？克隆体？<br>这究竟是什么意思啊……",
      "answer": ""
    },
    {
      "npc": "{user_nick}",
      "question": "<FONT color=#662500>详细的内容我也没听到。</FONT>",
      "answer": ""
    },
    {
      "npc": "高级魔法师斯泰拉",
      "question": "<FONT color=#7e12d2>（斯泰拉轻声叹息着）</FONT><br>谜团变得越来越多了…… 未来到底发生了什么事情？总是被牵着鼻子走，真烦啊。",
      "answer": ""
    },
    {
      "npc": "高级魔法师斯泰拉",
      "question": "嗯，反正，阿勒努特峡谷附近的古代寺院，据说那里好像是<FONT color=#a82424>英雄巴尔纳</FONT>的沉睡之地。没想到她会去那种地方。怪不得沙漠当中不见其任何踪影，哎！<br>\n<FONT color=#7e12d2>（很生气的样子）</FONT>",
      "answer": ""
    },
    {
      "npc": "高级魔法师斯泰拉",
      "question": "嗯，越想越气人啊。向宫里报告的事就交给我吧。<br>你赶紧和柯梅里纳一起前往古代寺院好好侦察一番。<br>百合花若是真在那里的话，必须得请求支援才是。",
      "answer": ""
    },
    {
      "npc": "{user_nick}",
      "question": "<FONT color=#7e12d2>（脸色苍白。似乎上次见面过后一点也没有休息的样子 ）</FONT>",
      "answer": ""
    },
    {
      "npc": "高级魔法师斯泰拉",
      "question": "居然把英雄沉睡的古代寺院视作根据地，胆量可真不小。<br>既然古代寺院已经被占领，看来要称其为<FONT color=#a82424>被占领的古代寺院</FONT>了……<br>祝你一路平安。",
      "answer": "",
      "image": "qw_75.png"
    },
    {
      "npc": "{user_nick}",
      "question": "<FONT color=#7e12d2>（脸色苍白。似乎上次见面过后一点也没有休息的样子 ）</FONT>",
      "answer": ""
    },
    {
      "npc": "学者柯梅里纳",
      "question": "这，怎么可能……",
      "answer": ""
    },
    {
      "npc": "{user_nick}",
      "question": "<FONT color=#662500>到底怎么了？百合花呢……？</FONT>",
      "answer": ""
    },
    {
      "npc": "学者柯梅里纳",
      "question": "是的，百合花从一开始就想得到黛西的宝玉……！<br>如果说黛西是我们的原型……那现在这个时期我和我的姐妹们应该还没诞生。宝玉应该还很完整，一定拥有强大的力量……但不知道为什么只把宝玉拿走……",
      "answer": ""
    },
    {
      "npc": "{user_nick}",
      "question": "<FONT color=#662500>有没有只利用宝玉就能做的事情？比如变成龙之类的……</FONT>",
      "answer": ""
    },
    {
      "npc": "学者柯梅里纳",
      "question": "<FONT color=#7e12d2>（摇了摇头）</FONT><FONT color=#2b2723>有太多不确定的因素了。之前也没有人验证过 ……</FONT>即便她现在夺走宝玉，也只可以制作像我们这种克隆体而已…… 啊！",
      "answer": ""
    },
    {
      "npc": "{user_nick}",
      "question": "<FONT color=#662500>制作克隆体？！？？！</FONT>",
      "answer": ""
    },
    {
      "npc": "学者柯梅里纳",
      "question": "没错。而且既然能够生产出我们，百合花肯定可以生产更强大的克隆体。将来还会生产、牺牲多少姊妹呢……<FONT color=#7e12d2>（柯梅里纳悲伤的眺望着百合花消失的方向）</FONT>",
      "answer": ""
    },
    {
      "npc": "学者柯梅里纳",
      "question": "……嗯？啊，什么问题？",
      "answer": ""
    },
    {
      "npc": "{user_nick}",
      "question": "<FONT color=#662500>……我知道黛西拥有宝玉……但她拥有哪种龙之宝玉呢？</FONT>",
      "answer": ""
    },
    {
      "npc": "学者柯梅里纳",
      "question": "……不知道。但是有必要调查一下。<br>如果是文献中有记载的龙，也许能知道它的弱点。<br>调查的任务就交给我吧。我会用未来的技术仔细进行调查的！",
      "answer": ""
    },
    {
      "npc": "{user_nick}",
      "question": "<FONT color=#662500>我知道了，那就拜托你了。</FONT>",
      "answer": ""
    },
    {
      "npc": "学者柯梅里纳",
      "question": "我要先对这里进行仔细的调查。<br>这是为了抢走宝玉而特地选择的地方，一定能找到和宝玉有关的资料。<br><FONT color=#387206>{user_nick}</FONT>，请别担心！<br><FONT color=#7e12d2>（柯梅里纳似乎已经下定决心。向神圣天堂的高级魔法师斯泰拉报告吧）</FONT>",
      "answer": ""
    },
    {
      "npc": "高级魔法师斯泰拉",
      "question": "我都等到望眼欲穿了，怎么样了？",
      "answer": ""
    },
    {
      "npc": "高级魔法师斯泰拉",
      "question": "\n<FONT color=#7e12d2>（转述期间发生的所有事情）</FONT><br>你说什么啊啊啊啊啊啊！？！？！？！<br>百合花从黛西身上取走了宝玉？<br>而且还是闪闪发光的龙之宝玉？？！！",
      "answer": ""
    },
    {
      "npc": "高级魔法师斯泰拉",
      "question": "思绪好乱……能不能讲些可以理清线索的事情啊。<br>嗯。我们先不谈重新制作克隆体的事情。<br>不过，那样的话，谜团可就越来越多了啊……",
      "answer": ""
    },
    {
      "npc": "{user_nick}",
      "question": "<FONT color=#662500>什么谜团？</FONT>",
      "answer": ""
    },
    {
      "npc": "高级魔法师斯泰拉",
      "question": "你想想……BR>如果<FONT color=#a82424>百合花知道黛西就是克隆体的原型……</FONT><br>那么，百合花就是直接制作克隆体的人或者是该计划的参与者。<br>柯梅里纳也提到过，所以这是可以肯定的事实。",
      "answer": ""
    },
    {
      "npc": "高级魔法师斯泰拉",
      "question": "不过<FONT color=#a82424>她是如何确定过去的黛西会出现在燃烧的泰尔罗萨市区的呢？</FONT>即便她对黛西非常了解，但是一般情况下一个年幼的少女怎么可能会出现在燃烧的市区呢？而且百合花作为龙的主导者，也不至于仅仅因为相信命运而前往市区的吧。",
      "answer": ""
    },
    {
      "npc": "高级魔法师斯泰拉",
      "question": "还有，<FONT color=#a82424>为何那个黛西拥有宝玉却没有变成龙呢？</FONT> 宝玉可是个很可怕的东西。弱者要是拥有它，其身体和心灵瞬间就会被宝玉吞噬。况且，持有宝玉的人居然是个年幼的少女……你也应该明白这是不可能的嘛。",
      "answer": "",
      "image": "qn_npc_charty.png"
    },
    {
      "npc": "{user_nick}",
      "question": "<FONT color=#662500>（说的是察提啊……）</FONT>",
      "answer": "",
      "image": "qn_npc_charty.png"
    },
    {
      "npc": "高级魔法师斯泰拉",
      "question": "谜团越来越多，却找不出解开它的方法，这可真让人头疼啊。<br>但愿柯梅里纳的调查能有什么成果啊。<br>对了，你看到百合花逃到哪里去了吗？",
      "answer": ""
    },
    {
      "npc": "{user_nick}",
      "question": "<FONT color=#662500>没有，她瞬间就消失了……</FONT>",
      "answer": ""
    },
    {
      "npc": "高级魔法师斯泰拉",
      "question": "闯了这么大的祸之后后，就这么消失了，难道还要引发什么更大的事情不成……想想就让人头疼啊，不过既然我们已经尽了最大努力，多少也能自我安心些了，辛苦你了。",
      "answer": ""
    },
    {
      "question": "任务奖励",
      "answer": ""
    },
    {
      "npc": "高级魔法师斯泰拉",
      "question": "对了，你看我这记性。<br>\n你刚来的时候，我就应该跟你说了。",
      "answer": ""
    },
    {
      "npc": "{user_nick}",
      "question": "\n<FONT color=#662500>什么事情？</FONT>",
      "answer": ""
    }
  ]
}