{
  "qkname": "黑暗灾难",
  "data": [
    {
      "npc": "小龙",
      "question": "快去见主教伊格纳西奥吧。",
      "answer": ""
    },
    {
      "npc": "主教伊格纳西奥",
      "question": "但是你说黑骑士的名字是贝思柯德吗？<br>真是贝思柯德的话，就出大事了……",
      "answer": ""
    },
    {
      "npc": "{user_nick}",
      "question": "<FONT color=#662500>虽然是50年前的事情了，不过应该是同一个人。该不是假冒的吧？</FONT>",
      "answer": ""
    },
    {
      "npc": "主教伊格纳西奥",
      "question": "我只告诉你一个人，不过贝思柯德其实曾经是我们的龙之追随者。但是现在他只是个叛徒。他用我们的技术得到不老的身体后就背叛了我们，真是厚颜无耻的家伙。",
      "answer": ""
    },
    {
      "npc": "主教伊格纳西奥",
      "question": "和阿尔杰塔在一起的那个剑客独自离开了？黑骑士真的是贝思柯德的话……他一个人可能有点吃力啊。<br>现在是不可能追上去的。<br><FONT color=#7e12d2>（28级之后才可进行此任务）</FONT>",
      "answer": ""
    },
    {
      "npc": "主教伊格纳西奥",
      "question": "和阿尔杰塔在一起的那个剑客独自离开了？黑骑士真的是贝思柯德的话……为什么不追上去而是立刻回来了呢？",
      "answer": ""
    },
    {
      "npc": "{user_nick}",
      "question": "<FONT color=#662500>据说是阿尔杰塔阻止了他。</FONT>",
      "answer": ""
    },
    {
      "npc": "主教伊格纳西奥",
      "question": "嗯。那么你去请求道格拉斯将军把军队派去黑暗领地守备队据点。精英士兵们就算在黑暗大君主领地取得一次胜利，王城也不会有什么反应的。",
      "answer": ""
    },
    {
      "npc": "主教伊格纳西奥",
      "question": "既然知道了带走先知的黑骑士是贝思柯德，我们不能束手待毙。 <br>他潜伏在我们龙之追随者内部，利用得到的情报做了些什么，我光是想想都害怕。事不宜迟。",
      "answer": ""
    },
    {
      "npc": "道格拉斯将军",
      "question": "斯图尔特公爵讨厌兽人，所以你还是不要进出王城为好。 <br>我虽然能理解你郁闷的心情，但是这也没办法。",
      "answer": ""
    },
    {
      "npc": "杰兰特",
      "question": "……不要妨碍我。我正在寻找那个人的位置。",
      "answer": ""
    },
    {
      "npc": "小龙",
      "question": "<FONT color=#7e12d2>（去黑山山角看看吧）</FONT>"
    },
    {
      "npc": "主教伊格纳西奥",
      "question": "那么你快点出发去黑暗领地守备队据点吧。道格拉斯将军马上就会派精锐士兵去的。",
      "answer": ""
    },
    {
      "npc": "杰兰特",
      "question": "……我来晚了一步。<br><FONT color=#7e12d2>（杰兰特盯着一个方向）</FONT>",
      "answer": ""
    },
    {
      "npc": "杰兰特",
      "question": "这里面的巢穴已经完成了，所以从这里开始就无法靠近了。",
      "answer": ""
    },
    {
      "npc": "{user_nick}",
      "question": "<FONT color=#662500>巢穴？那是什么……啊，又来……呃呃呃！</FONT>",
      "answer": ""
    },
    {
      "npc": "杰兰特",
      "question": "看起来你的手臂很疼啊。你去村子里接受治疗吧。<br>关于巢穴的事，我之后再告诉你。",
      "answer": ""
    },
    {
      "npc": "杰兰特",
      "question": "….<br><FONT color=#7e12d2>（似乎不想再继续对话了。去找主教伊格纳西奥吧）</FONT>",
      "answer": ""
    },
    {
      "npc": "主教伊格纳西奥",
      "question": "<FONT color=#387206>{user_nick}</FONT>，你的手臂怎么成那样了？<br>呼吸也很困难……难道是遇上了黑骑士吗？",
      "answer": ""
    },
    {
      "npc": "{user_nick}",
      "question": "<FONT color=#662500>您没读埃雷娜写的信吗？</FONT>",
      "answer": ""
    },
    {
      "question": "任务奖励",
      "answer": ""
    },
    {
      "npc": "主教伊格纳西奥",
      "question": "埃雷娜的信？啊啊，读是读了。 ",
      "answer": ""
    }
  ]
}