{
  "qkname": "净化装置",
  "data": [
    {
      "npc": "小龙",
      "question": "<FONT color=#387206>{user_nick}</FONT> 现在出大事了！夏洛特和埃雷娜打了一架，结果现在凯德拉关卡要被污染了。<br>我们现在也在这里，不能什么都不做啊！",
      "answer": ""
    },
    {
      "npc": "{user_nick}",
      "question": "<FONT color=#662500>你想要逃跑吗？</FONT>",
      "answer": ""
    },
    {
      "npc": "小龙",
      "question": "ndnpc_Shaolung_9587_qu_01.ogg}<br>咔……咔！你以为我会主张逃跑吗？你如果这么想，就太小瞧我这个武者的心志了！<br>我是绝对……绝对不会那么做的！现在不是讨论这个的时候，得赶紧去想办法净化凯德拉关卡才行！",
      "answer": ""
    },
    {
      "npc": "{user_nick}",
      "question": "<FONT color=#662500>没有净化的方法吗？</FONT>",
      "answer": ""
    },
    {
      "npc": "小龙",
      "question": "ndnpc_Shaolung_9587_qu_02.ogg}<br>咔，埃提亚和夏洛特已经去解决了，我们好像没必要非得出面……<br>魔法师缇娜说她对净化装置有过研究，所以去找她了。",
      "answer": ""
    },
    {
      "npc": "高级魔法师缇娜",
      "question": "听说凯德拉充满了污染物质。这究竟是怎么回事……啧！",
      "answer": ""
    },
    {
      "npc": "阿尔杰塔",
      "question": "人类怎么因为这点毒就大惊小怪的……<br>埃雷娜那女人真是，都死了还要来搅浑水。哼！",
      "answer": ""
    },
    {
      "npc": "{user_nick}",
      "question": "<FONT color=#662500>（还没整理好，但还是去见魔法师缇娜吧）</FONT>",
      "answer": ""
    },
    {
      "npc": "高级魔法师缇娜",
      "question": "你就是那个传说中的兽人，<FONT color=#387206>{user_nick}</FONT>？你也是因为污染物质扩散才来的吗？<br>我正好也在找有没有能帮上忙的事情。",
      "answer": ""
    },
    {
      "npc": "高级魔法师缇娜",
      "question": "不过话说回来，你是兽人，所以是在莲花沼泽长大的吧？ 卡拉秋大人最近怎么样了？ <br>那位大人身为魔法师的英雄，居然定居在莲花沼泽，你们都得感激不尽才行。<br>你们这些原住民不会欺负卡拉秋大人吧？",
      "answer": ""
    },
    {
      "npc": "{user_nick}",
      "question": "<FONT color=#662500>卡拉秋? 我不知道有这么个人。</FONT>",
      "answer": ""
    },
    {
      "npc": "高级魔法师缇娜",
      "question": "什么？居然？！？你说不知道魔法师英雄卡拉秋？？<br>你知道魔物抗战吗？不知道？兽人们究竟是怎么教育孩子的啊？ <br>究竟是多么落后的村子，连这个都不教吗？",
      "answer": ""
    },
    {
      "npc": "{user_nick}",
      "question": "<FONT color=#662500>请不要说我们村的坏话！<br>因为陨石，我们村的人要生活都很困难了。教育什么的……</FONT>",
      "answer": ""
    },
    {
      "npc": "高级魔法师缇娜",
      "question": "陨石？啊……是这样啊。我在魔法师的集会上似乎听到过那件事。大家都担心卡拉秋大人是不是受伤了。如果村里发生过那样的事情的话，我为刚才说的话道歉。<br>嗯，但是记住了，你关心的净化装置本来是在卡拉秋大人的命令之下开始研究的。",
      "answer": ""
    },
    {
      "npc": "高级魔法师缇娜",
      "question": "但是我的师父在魔物抗战中突然牺牲之后，有关净化装置的研究不得不中断了。",
      "answer": ""
    },
    {
      "npc": "高级魔法师缇娜",
      "question": "虽然很遗憾，但是在师父去世的死亡盆地应该有研究材料，可是谁都不知道文件究竟在哪里。",
      "answer": ""
    },
    {
      "npc": "{user_nick}",
      "question": "<FONT color=#662500>我去看看。</FONT>",
      "answer": ""
    },
    {
      "npc": "高级魔法师缇娜",
      "question": "你在说什么呢？死亡盆地可是非常危险的地方啊。<br>毒物四散，污染也很严重，你还是不要去比较好。",
      "answer": ""
    },
    {
      "npc": "{user_nick}",
      "question": "<FONT color=#662500>（想要治疗埃雷娜的话，必须要了解净化装置才行。）<br>那种程度我还是能忍受的。</FONT>",
      "answer": ""
    },
    {
      "npc": "高级魔法师缇娜",
      "question": "师父的研究资料应该就在他去世的死亡盆地。虽然能拿到研究资料的话是好事，但是你不要太勉强了。!",
      "answer": ""
    },
    {
      "npc": "阿尔杰塔",
      "question": "你真的打算去死亡盆地吗？<br>没什么必要连你也非得去啊……",
      "answer": "",
      "image": "qw_24.png"
    },
    {
      "npc": "{user_nick}",
      "question": "<FONT color=#662500>哼，比起我这个兽人来说，你还是更信任夏洛特吧？</FONT>",
      "answer": ""
    },
    {
      "npc": "阿尔杰塔",
      "question": "哼，我只是还需要有人帮我跑腿而已。对你来说很危险，所以去之前，收下这个吧。<br>不准受伤，平安回来！这可是命令啊，知道了吧？",
      "answer": ""
    },
    {
      "npc": "{user_nick}",
      "question": "<FONT color=#662500>（她是在为我担心吗？）切……谢了。</FONT>",
      "answer": ""
    },
    {
      "npc": "阿尔杰塔",
      "question": "就凭你的实力要去死亡盆地还不太勉强了，所以我才帮你的。别误会了。<br>啊，对了。那个东西效果不会持续很久，你差不多处理好就回来吧。",
      "answer": ""
    },
    {
      "npc": "小龙",
      "question": "嗯……<br><FONT color=#7e12d2>（去找高级魔法师缇娜吧）</FONT>",
      "answer": ""
    },
    {
      "npc": "阿尔杰塔",
      "question": "你活着回来了啊。你做了该做的事呢。",
      "answer": ""
    },
    {
      "npc": "高级魔法师缇娜",
      "question": "谢谢你。唉……结果还是借助别人的力量找回的。",
      "answer": ""
    },
    {
      "question": "任务奖励",
      "answer": ""
    },
    {
      "npc": "高级魔法师缇娜",
      "question": "经过对文件的解读，嗯……好像是有办法的。这里写着“古代人用于向凯德拉周边的森林注入生命力的古代机械装置”。",
      "answer": ""
    },
    {
      "npc": "高级魔法师缇娜",
      "question": "不知道用这个净化装置，能不能让荒废的死亡森林恢复原貌。",
      "answer": ""
    },
    {
      "npc": "高级魔法师缇娜",
      "question": "据说在古代人的知识当中，有一种可以解除物质毒性的净化装置。这个文件中就记录了那个净化装置的相关内容。",
      "answer": ""
    }
  ]
}