{
  "qkname": "可疑的帮助",
  "data": [
    {
      "npc": "诺尔佩",
      "question": "留下了一些类似药草的东西……<br>莫非<FONT color=#387206>{user_nick}</FONT>大人中毒了？",
      "answer": ""
    },
    {
      "npc": "{user_nick}",
      "question": "<FONT color=#662500>啊……刚刚在旧街被守卫者的树根刺伤了……</FONT>",
      "answer": ""
    },
    {
      "npc": "诺尔佩",
      "question": "可恶……沉睡在旧街的守卫者是过去卡伊伦岛的土著民们<br>为了守护自己的城市，通过炼金术制成的。",
      "answer": ""
    },
    {
      "npc": "诺尔佩",
      "question": "如今失去了主人，守护城市成了他们存在的唯一价值，所以才会胡乱攻击所有来客。通过炼金术制成的守卫者身上，缠绕着层层树根，上面含有剧毒。普通人一旦被砍伤，就会立刻身亡。",
      "answer": ""
    },
    {
      "npc": "{user_nick}",
      "question": "<FONT color=#662500>嗬！这、这！我被树根刺伤了！那我岂不是死定了？</FONT>",
      "answer": ""
    },
    {
      "npc": "诺尔佩",
      "question": "<FONT color=#7e12d2>（诺尔佩查看了一下伤口。）</FONT><br>幸好<FONT color=#387206>{user_nick}</FONT>大人体质特殊，拥有多个龙族的庇护以及红龙的半块宝玉，生命没什么大碍。",
      "answer": ""
    },
    {
      "npc": "诺尔佩",
      "question": "可要是放任不管，日后在行动时一定有所影响。<br>如果杰兰特大人调查的药草是解毒草，还是吃下药草解毒为好。",
      "answer": ""
    },
    {
      "npc": "{user_nick}",
      "question": "<FONT color=#662500>诺尔佩你好像几乎确信那药草就是解毒草？</FONT>",
      "answer": ""
    },
    {
      "npc": "诺尔佩",
      "question": "我也没有确切的理由，完全是凭直觉。<br>也许留下毒草是为了杀人，但如果真是这样，那人在尾随途中完全可以尝试其他的办法，不是吗？",
      "answer": ""
    },
    {
      "npc": "{user_nick}",
      "question": "<FONT color=#662500>也就是留下药草的不是敌人，而是战友……<br>难道是贝勒尼卡的人？</FONT>",
      "answer": ""
    },
    {
      "npc": "诺尔佩",
      "question": "有这个可能……但即便如此，贝勒尼卡也绝不会承认。<br>如果承认偷偷安排了密探，那岂不是明摆着告诉大家，他不相信我们。 ",
      "answer": ""
    },
    {
      "npc": "诺尔佩",
      "question": "嗯……坐船是进出卡伊伦岛的唯一手段。<br>如果去追问梅尔卡港口的船长，说不定能挖到什么消息？我听说他正好来梅尔卡市国办事。",
      "answer": ""
    },
    {
      "npc": "诺尔佩",
      "question": "我认为，如果杰兰特大人调查的药草确实是解毒草<br>那大可放下心来，继续展开调查。一旦排除了危险要素，就没必要再拖延下去。",
      "answer": ""
    },
    {
      "npc": "{user_nick}",
      "question": "<FONT color=#662500>嗯，我也赞同。<br>眼下还是去梅尔卡问问船长，看他是否知道谁曾进入过卡伊伦岛。</FONT><br>\n<FONT color=#662500>他目前人在梅尔卡吗？ </FONT>",
      "answer": ""
    },
    {
      "npc": "诺尔佩",
      "question": "到时候问问<FONT color=#a82424>船长赫克托</FONT>，除了<FONT color=#387206>{user_nick}</FONT>大人一行之外，还有没有其他人进入过卡伊伦岛，一定能打探出线索。",
      "answer": "",
      "image": "qn_hector.png"
    },
    {
      "npc": "船长赫克托",
      "question": "哦哦，是你啊！我借给你的船还好用吗？",
      "answer": ""
    },
    {
      "npc": "{user_nick}",
      "question": "<FONT color=#662500>那个……船长大人，除了我们之外，不知道还有没有其他人跟您借船前往卡伊伦岛？</FONT>",
      "answer": ""
    },
    {
      "npc": "船长赫克托",
      "question": "嗯？ <FONT color=#7e12d2>（船长犹豫片刻问道。）</FONT><br>谁都知道，卡伊伦岛上的查尔德是什么来头，除了你们，谁还有这个胆子……",
      "answer": ""
    },
    {
      "npc": "{user_nick}",
      "question": "<FONT color=#662500>不怕一万就怕万一嘛。<br>真的一个人也没有？比如说贝勒尼卡大人的人……我一定保密！</FONT>",
      "answer": ""
    },
    {
      "npc": "船长赫克托",
      "question": "真是的……你忘了我也是梅尔卡的人吗？<br>当然，作为梅尔卡的忠实者，即使有种事，我也不会告诉你，但我可以用对天起誓，贝勒尼卡大人从未对我下达过这种指示。",
      "answer": ""
    },
    {
      "npc": "{user_nick}",
      "question": "<FONT color=#662500>（刚刚的短暂犹豫，莫非只是巧合……？）<br>好吧。我知道了。</FONT>",
      "answer": ""
    },
    {
      "npc": "船长赫克托",
      "question": "你这人，看来已经跟我混熟了。 <br>竟然连这种问题也毫无忌讳。哈哈。",
      "answer": ""
    },
    {
      "npc": "船长赫克托",
      "question": "\n<FONT color=#7e12d2>（看来要先跟杰兰特见一面。）</FONT>",
      "answer": "",
      "image": "qn_npc_geraint_kid.png"
    },
    {
      "npc": "杰兰特",
      "question": "你来得正好。有关药草的调查刚刚结束。",
      "answer": ""
    },
    {
      "npc": "{user_nick}",
      "question": "<FONT color=#662500>是吗？结果如何？</FONT>",
      "answer": ""
    },
    {
      "npc": "杰兰特",
      "question": "这是奇怪了……尾随我们的家伙留下的竟然是解毒草。",
      "answer": ""
    },
    {
      "question": "任务奖励",
      "answer": ""
    },
    {
      "npc": "{user_nick}",
      "question": "<FONT color=#662500>果然如此……诺尔佩真的没猜错……</FONT>",
      "answer": ""
    }
  ]
}